README.txt
setup.py
delegator/__init__.py
delegator/delegator.py
delegator.egg-info/PKG-INFO
delegator.egg-info/SOURCES.txt
delegator.egg-info/dependency_links.txt
delegator.egg-info/top_level.txt
test/tests_delegator.py