Metadata-Version: 1.0
Name: delegator
Version: 0.0.3
Summary: UNKNOWN
Home-page: https://github.com/hugobast/delegator
Author: Hugo Bastien
Author-email: hugobast@gmail.com
License: MIT License
Platform: UNKNOWN
